{
  "items": [
    {
      "type": "group",
      "ctime": 1727064486989,
      "items": [
        {
          "type": "group",
          "ctime": 1727064486989,
          "items": [
            {
              "type": "file",
              "ctime": 1727064502147,
              "path": "1. Main/My books.md",
              "subpath": "#^-"
            },
            {
              "type": "group",
              "ctime": 1727064506454,
              "items": [],
              "title": "Social sciences"
            },
            {
              "type": "file",
              "ctime": 1727064502147,
              "path": "1. Main/My books.md",
              "subpath": "#^-"
            },
            {
              "type": "file",
              "ctime": 1727064486989,
              "path": "5. Metadata/Sample hierarchy.md",
              "subpath": "#^-"
            },
            {
              "type": "group",
              "ctime": 1727064506454,
              "items": [],
              "title": "Social sciences"
            }
          ],
          "title": "1. Main"
        },
        {
          "type": "group",
          "ctime": 1727064542866,
          "items": [],
          "title": "2. Pradeep"
        },
        {
          "type": "group",
          "ctime": 1727064542866,
          "items": [],
          "title": "3. Youtube"
        },
        {
          "type": "group",
          "ctime": 1727064542866,
          "items": [],
          "title": "4. Books"
        },
        {
          "type": "group",
          "ctime": 1727064542866,
          "items": [],
          "title": "5. Metadata"
        },
        {
          "type": "group",
          "ctime": 1727064542866,
          "items": [],
          "title": "6. Read later"
        },
        {
          "type": "file",
          "ctime": 1727064542866,
          "path": "Scribble.md",
          "subpath": "#^-"
        }
      ],
      "title": "sortspec"
    }
  ]
}